ppdir/__init__.py
ppdir-0.1.0.dist-info/LICENSE
ppdir-0.1.0.dist-info/METADATA
ppdir-0.1.0.dist-info/WHEEL
ppdir-0.1.0.dist-info/entry_points.txt
ppdir-0.1.0.dist-info/top_level.txt
ppdir-0.1.0.dist-info/RECORD
