Metadata-Version: 2.1
Name: ppdir
Version: 0.1.0
Summary: Pretty print a directory structure as a tree
Home-page: https://github.com/EClaesson/ppdir
Author: Emanuel Claesson
Author-email: emanuel.claesson@gmail.com
License: UNKNOWN
Platform: UNKNOWN
Classifier: Programming Language :: Python :: 3
Classifier: License :: OSI Approved :: MIT License
Classifier: Operating System :: OS Independent
Requires-Python: >=3.5
Requires-Dist: colorama (>=0.4.3)
